chatgpt_aitools/__init__.py
chatgpt_aitools/build.py
chatgpt_aitools-0.2.0.dist-info/METADATA
chatgpt_aitools-0.2.0.dist-info/WHEEL
chatgpt_aitools-0.2.0.dist-info/top_level.txt
chatgpt_aitools-0.2.0.dist-info/RECORD
