Metadata-Version: 2.4
Name: chatgpt_aitools
Version: 0.2.0
Summary: Short description of your package
Author: chatgpt_aitools
Classifier: Programming Language :: Python :: 3
Classifier: License :: OSI Approved :: MIT License
Requires-Python: >=3.6
Dynamic: author
Dynamic: classifier
Dynamic: description-content-type
Dynamic: requires-python
Dynamic: summary
